odoo/addons/purchase_work_acceptance_invoice_plan/README.rst
odoo/addons/purchase_work_acceptance_invoice_plan/__init__.py
odoo/addons/purchase_work_acceptance_invoice_plan/__manifest__.py
odoo/addons/purchase_work_acceptance_invoice_plan/data/server_action.xml
odoo/addons/purchase_work_acceptance_invoice_plan/i18n/it.po
odoo/addons/purchase_work_acceptance_invoice_plan/i18n/purchase_work_acceptance_invoice_plan.pot
odoo/addons/purchase_work_acceptance_invoice_plan/models/__init__.py
odoo/addons/purchase_work_acceptance_invoice_plan/models/purchase.py
odoo/addons/purchase_work_acceptance_invoice_plan/models/work_acceptance.py
odoo/addons/purchase_work_acceptance_invoice_plan/readme/CONTRIBUTORS.md
odoo/addons/purchase_work_acceptance_invoice_plan/readme/DESCRIPTION.md
odoo/addons/purchase_work_acceptance_invoice_plan/readme/USAGE.md
odoo/addons/purchase_work_acceptance_invoice_plan/security/ir.model.access.csv
odoo/addons/purchase_work_acceptance_invoice_plan/static/description/icon.png
odoo/addons/purchase_work_acceptance_invoice_plan/static/description/index.html
odoo/addons/purchase_work_acceptance_invoice_plan/tests/__init__.py
odoo/addons/purchase_work_acceptance_invoice_plan/tests/test_purchase_work_acceptance_invoice_plan.py
odoo/addons/purchase_work_acceptance_invoice_plan/views/purchase_views.xml
odoo/addons/purchase_work_acceptance_invoice_plan/views/work_acceptance_view.xml
odoo/addons/purchase_work_acceptance_invoice_plan/wizard/__init__.py
odoo/addons/purchase_work_acceptance_invoice_plan/wizard/select_work_acceptance_invoice_plan_wizard.py
odoo/addons/purchase_work_acceptance_invoice_plan/wizard/select_work_acceptance_invoice_plan_wizard_views.xml
odoo/addons/purchase_work_acceptance_invoice_plan/wizard/select_work_acceptance_wizard.py
odoo_addon_purchase_work_acceptance_invoice_plan-18.0.1.0.0.5.dist-info/METADATA
odoo_addon_purchase_work_acceptance_invoice_plan-18.0.1.0.0.5.dist-info/WHEEL
odoo_addon_purchase_work_acceptance_invoice_plan-18.0.1.0.0.5.dist-info/top_level.txt
odoo_addon_purchase_work_acceptance_invoice_plan-18.0.1.0.0.5.dist-info/RECORD
